voicecord/__init__.py
voicecord-2.1.5.dist-info/LICENSE
voicecord-2.1.5.dist-info/METADATA
voicecord-2.1.5.dist-info/WHEEL
voicecord-2.1.5.dist-info/top_level.txt
voicecord-2.1.5.dist-info/RECORD
