Metadata-Version: 2.1
Name: voicecord
Version: 2.1.5
Summary: A simple yet powerful voice recording package for Discord
Home-page: https://github.com/petertill/voicecord
Author: Peter Till
Author-email: ptertill@gmail.com
License: MIT
Requires-Python: >=3.8
License-File: LICENSE
Requires-Dist: pynacl
